Metadata-Version: 2.1
Name: octconv
Version: 0.2.0
Summary: Octave Convolution Implementation in PyTorch
Home-page: https://github.com/braincreators/octconv
Author: BrainCreators
Author-email: miguel@braincreators.com
License: MIT
Platform: UNKNOWN
